[{"batter_name":"Max Clark","BIP":109,"GB":53,"GB%":48.6,"Low-LD":9,"Low-LD%":8.3,"High-LD":10,"High-LD%":9.2,"FB":25,"FB%":22.9,"PU":11,"PU%":10.1}, 
 {"batter_name":"League","BIP":103,"GB":45.4887640449438202,"GB%":43.8,"Low-LD":11.7078651685393258,"Low-LD%":11.3,"High-LD":13.6629213483146067,"High-LD%":13.1,"FB":24.6629213483146067,"FB%":23.7,"PU":9.9382022471910112,"PU%":9.6}, 
 {"batter_name":"Gage Workman","BIP":95,"GB":32,"GB%":33.7,"Low-LD":22,"Low-LD%":23.2,"High-LD":18,"High-LD%":18.9,"FB":19,"FB%":20.0,"PU":4,"PU%":4.2}, 
 {"batter_name":"Ben Malgeri","BIP":92,"GB":44,"GB%":47.8,"Low-LD":11,"Low-LD%":12.0,"High-LD":15,"High-LD%":16.3,"FB":21,"FB%":22.8,"PU":3,"PU%":3.3}, 
 {"batter_name":"Eduardo Valencia","BIP":89,"GB":41,"GB%":46.1,"Low-LD":10,"Low-LD%":11.2,"High-LD":11,"High-LD%":12.4,"FB":20,"FB%":22.5,"PU":6,"PU%":6.7}, 
 {"batter_name":"Jace Jung","BIP":81,"GB":34,"GB%":42.0,"Low-LD":9,"Low-LD%":11.1,"High-LD":15,"High-LD%":18.5,"FB":18,"FB%":22.2,"PU":7,"PU%":8.6}, 
 {"batter_name":"Corey Julks","BIP":73,"GB":28,"GB%":38.4,"Low-LD":7,"Low-LD%":9.6,"High-LD":10,"High-LD%":13.7,"FB":20,"FB%":27.4,"PU":8,"PU%":11.0}, 
 {"batter_name":"Max Burt","BIP":60,"GB":28,"GB%":46.7,"Low-LD":5,"Low-LD%":8.3,"High-LD":5,"High-LD%":8.3,"FB":13,"FB%":21.7,"PU":9,"PU%":15.0}, 
 {"batter_name":"Tomás Nido","BIP":51,"GB":17,"GB%":33.3,"Low-LD":10,"Low-LD%":19.6,"High-LD":6,"High-LD%":11.8,"FB":13,"FB%":25.5,"PU":7,"PU%":13.7}, 
 {"batter_name":"Tyler Gentry","BIP":49,"GB":22,"GB%":44.9,"Low-LD":7,"Low-LD%":14.3,"High-LD":8,"High-LD%":16.3,"FB":8,"FB%":16.3,"PU":5,"PU%":10.2}, 
 {"batter_name":"Trei Cruz","BIP":46,"GB":20,"GB%":43.5,"Low-LD":6,"Low-LD%":13.0,"High-LD":5,"High-LD%":10.9,"FB":7,"FB%":15.2,"PU":7,"PU%":15.2}, 
 {"batter_name":"Cal Stevenson","BIP":38,"GB":14,"GB%":36.8,"Low-LD":8,"Low-LD%":21.1,"High-LD":8,"High-LD%":21.1,"FB":7,"FB%":18.4,"PU":2,"PU%":5.3}, 
 {"batter_name":"Wenceel Pérez","BIP":37,"GB":10,"GB%":27.0,"Low-LD":7,"Low-LD%":18.9,"High-LD":5,"High-LD%":13.5,"FB":10,"FB%":27.0,"PU":7,"PU%":18.9}, 
 {"batter_name":"Luke Ritter","BIP":23,"GB":15,"GB%":65.2,"Low-LD":1,"Low-LD%":4.3,"High-LD":1,"High-LD%":4.3,"FB":2,"FB%":8.7,"PU":4,"PU%":17.4}, 
 {"batter_name":"Max Anderson","BIP":20,"GB":11,"GB%":55.0,"Low-LD":4,"Low-LD%":20.0,"High-LD":2,"High-LD%":10.0,"FB":3,"FB%":15.0,"PU":0,"PU%":0.0}, 
 {"batter_name":"Andrew Navigato","BIP":20,"GB":8,"GB%":40.0,"Low-LD":4,"Low-LD%":20.0,"High-LD":3,"High-LD%":15.0,"FB":5,"FB%":25.0,"PU":1,"PU%":5.0}, 
 {"batter_name":"Hao-Yu  Lee","BIP":19,"GB":8,"GB%":42.1,"Low-LD":2,"Low-LD%":10.5,"High-LD":2,"High-LD%":10.5,"FB":6,"FB%":31.6,"PU":2,"PU%":10.5}, 
 {"batter_name":"Zach McKinstry","BIP":7,"GB":3,"GB%":42.9,"Low-LD":0,"Low-LD%":0.0,"High-LD":2,"High-LD%":28.6,"FB":2,"FB%":28.6,"PU":0,"PU%":0.0}, 
 {"batter_name":"Paul DeJong","BIP":5,"GB":3,"GB%":60.0,"Low-LD":0,"Low-LD%":0.0,"High-LD":0,"High-LD%":0.0,"FB":2,"FB%":40.0,"PU":0,"PU%":0.0}, 
 {"batter_name":"Zack Short","BIP":3,"GB":2,"GB%":66.7,"Low-LD":1,"Low-LD%":33.3,"High-LD":1,"High-LD%":33.3,"FB":0,"FB%":0.0,"PU":0,"PU%":0.0}]
